setup.py
django_initkit.egg-info/PKG-INFO
django_initkit.egg-info/SOURCES.txt
django_initkit.egg-info/dependency_links.txt
django_initkit.egg-info/top_level.txt
initkit/__init__.py
initkit/django_initkit.py
initkit/init_app/__init__.py
initkit/init_app/management/__init__.py
initkit/init_app/management/commands/__init__.py
initkit/init_app/management/commands/startproject.py
initkit/templates/__init__.py
initkit/templates/project_template/__init__.py
initkit/templates/project_template/manage.py
initkit/templates/project_template/settings.py
initkit/templates/project_template/settings_local.py
initkit/templates/project_template/urls.py
initkit/templates/project_template/wsgi.py